AgentEngine/__init__.py
AgentEngine/core/__init__.py
AgentEngine/core/agents/__init__.py
AgentEngine/core/agents/code_agent.py
AgentEngine/core/models/__init__.py
AgentEngine/core/models/embedding_model.py
AgentEngine/core/models/openai_llm.py
AgentEngine/core/models/openai_vlm.py
AgentEngine/core/models/stt_model.py
AgentEngine/core/models/tts_model.py
AgentEngine/core/prompts/code_agent.yaml
AgentEngine/core/prompts/code_agent_demo.yaml
AgentEngine/core/prompts/title_generator.yaml
AgentEngine/core/tools/__init__.py
AgentEngine/core/tools/bocha_search_tool.py
AgentEngine/core/tools/exa_search_tool.py
AgentEngine/core/tools/final_answer_format_tool.py
AgentEngine/core/tools/kb_search_tool.py
AgentEngine/core/utils/__init__.py
AgentEngine/core/utils/agent_utils.py
AgentEngine/core/utils/image_filter.py
AgentEngine/core/utils/observer.py
AgentEngine/core/utils/title_generator.py
AgentEngine/core/utils/tools_common_message.py
AgentEngine/data_cleanse/__init__.py
AgentEngine/data_cleanse/async_task_manager.py
AgentEngine/data_cleanse/cleanse_worker_pool.py
AgentEngine/data_cleanse/core.py
AgentEngine/data_cleanse/excel_clean.py
AgentEngine/data_cleanse/task_store.py
AgentEngine/data_cleanse/example_docs/logger.py
AgentEngine/vector_database/elasticsearch_core.py
AgentEngine/vector_database/utils.py
agentengine-0.1.8.dist-info/METADATA
agentengine-0.1.8.dist-info/WHEEL
agentengine-0.1.8.dist-info/top_level.txt
agentengine-0.1.8.dist-info/RECORD
