Metadata-Version: 2.4
Name: AgentEngine
Version: 0.1.8
Summary: AgentEngine 智能体框架
Author: Shuangrui Chen, Simeng Bian, Jingyuan Li, Mingchen Wan
Keywords: agent,ai,framework
Classifier: Development Status :: 4 - Beta
Classifier: Intended Audience :: Developers
Classifier: Programming Language :: Python :: 3
Classifier: Programming Language :: Python :: 3.10
Classifier: Programming Language :: Python :: 3.11
Requires-Python: >=3.10
Requires-Dist: aiofiles>=24.1.0
Requires-Dist: elasticsearch==8.17.2
Requires-Dist: exa_py>=1.9.1
Requires-Dist: fastapi>=0.115.12
Requires-Dist: httpx>=0.28.1
Requires-Dist: numpy>=1.26.4
Requires-Dist: openai>=1.69.0
Requires-Dist: openpyxl>=3.1.5
Requires-Dist: psycopg2-binary>=2.9.10
Requires-Dist: pydantic>=2.11.1
Requires-Dist: python-dotenv>=1.1.0
Requires-Dist: PyYAML>=6.0.1
Requires-Dist: Requests>=2.32.3
Requires-Dist: rich>=13.9.4
Requires-Dist: setuptools>=75.1.0
Requires-Dist: starlette>=0.46.1
Requires-Dist: unstructured>=0.17.2
Requires-Dist: uvicorn>=0.34.0
Requires-Dist: websockets>=14.2
Requires-Dist: smolagents==1.12.0
Requires-Dist: Pillow>=10.0.0
Requires-Dist: transformers>=4.36.0
Requires-Dist: torch>=2.0.0
Requires-Dist: aiohttp>=3.1.13
Provides-Extra: quality
Requires-Dist: ruff>=0.9.0; extra == "quality"
Provides-Extra: test
Requires-Dist: pytest>=8.1.0; extra == "test"
Provides-Extra: dev
Requires-Dist: AgentEngine[quality,test]; extra == "dev"
